datacker/__init__.py
datacker/builder.py
datacker/cli.py
datacker/fs.py
datacker/tests/__init__.py
datacker/tests/notebooks/test.ipynb
datacker/tests/test_builder.py
datacker/tests/test_cli.py
datacker/tests/test_fs.py
datacker-0.1.5.dist-info/entry_points.txt
datacker-0.1.5.dist-info/LICENSE
datacker-0.1.5.dist-info/WHEEL
datacker-0.1.5.dist-info/METADATA
datacker-0.1.5.dist-info/RECORD
