Metadata-Version: 2.1
Name: datacker
Version: 0.1.5
Summary: 
Author: Cristóbal Carnero Liñán
Author-email: ccarnerolinan@gmail.com
Requires-Python: >=3.7,<4.0
Classifier: Programming Language :: Python :: 3
Classifier: Programming Language :: Python :: 3.7
Classifier: Programming Language :: Python :: 3.8
Classifier: Programming Language :: Python :: 3.9
Requires-Dist: docker (>=4.4.1,<5.0.0)
Requires-Dist: typer (>=0.3.2,<0.4.0)
